<Ui>
  <Button name="BaganatorRetailTabButtonTemplate" virtual="true" inherits="PanelTabButtonTemplate">
    <Scripts>
      <OnShow>
        PanelTemplates_TabResize(self, 30, nil, 20)
        PanelTemplates_DeselectTab(self)
      </OnShow>
    </Scripts>
  </Button>

  <Button name="BaganatorClassicTabButtonTemplate" virtual="true" inherits="CharacterFrameTabButtonTemplate">
    <Scripts>
      <OnShow>
        PanelTemplates_TabResize(self, 30, nil, 20)
        PanelTemplates_DeselectTab(self)
      </OnShow>
    </Scripts>
  </Button>

  <CheckButton name="BaganatorRightSideTabButtonTemplate" virtual="true" scale="0.8">
    <Size>
      <AbsDimension x="32" y="32"/>
    </Size>
    <Layers>
      <Layer level="BACKGROUND">
        <Texture file="Interface\SpellBook\SpellBook-SkillLineTab">
          <Size>
            <AbsDimension x="64" y="64"/>
          </Size>
          <Anchors>
            <Anchor point="TOPLEFT">
              <Offset>
                <AbsDimension x="-3" y="11"/>
              </Offset>
            </Anchor>
          </Anchors>
        </Texture>
      </Layer>
      <Layer level="ARTWORK">
        <Texture parentKey="SelectedTexture" file="Interface\Buttons\CheckButtonHilight" alphaMode="ADD"/>
        <Texture parentKey="Icon" alphaMode="ADD" setAllPoints="true"/>
      </Layer>
    </Layers>
    <NormalTexture/>
    <HighlightTexture file="Interface\Buttons\ButtonHilight-Square" alphaMode="ADD"/>
    <Scripts>
      <OnEnter>
        GameTooltip:SetOwner(self, "ANCHOR_LEFT")
        GameTooltip:SetText(self.tabName)
        GameTooltip:Show()
      </OnEnter>
      <OnLeave>
        GameTooltip:Hide()
      </OnLeave>
    </Scripts>
  </CheckButton>

  <Button name="BaganatorTooltipIconButtonTemplate" virtual="true" inherits="UIPanelButtonTemplate">
    <Size x="32" y="22"/>
    <Scripts>
      <OnEnter>
        GameTooltip:SetOwner(self, "ANCHOR_RIGHT")
        GameTooltip:SetText(self.tooltipHeader)
        if self.tooltipText then
          GameTooltip:AddLine(self.tooltipText, 1, 1, 1, true)
        end
        GameTooltip:Show()
      </OnEnter>
      <OnLeave>
        GameTooltip:Hide()
      </OnLeave>
    </Scripts>
  </Button>

  <Button name="BaganatorCustomiseButtonTemplate" virtual="true" inherits="BaganatorTooltipIconButtonTemplate">
    <KeyValues>
      <KeyValue key="tooltipHeader" value="BAGANATOR_L_CUSTOMISE_BAGANATOR" type="global"/>
    </KeyValues>
    <Layers>
      <Layer level="ARTWORK">
        <Texture file="Interface\WorldMap\Gear_64">
          <TexCoords left="0.5" top="0" right="0" bottom="0.5"/>
          <Size x="19" y="19"/>
          <Anchors>
            <Anchor point="CENTER"/>
          </Anchors>
        </Texture>
      </Layer>
    </Layers>
    <Scripts>
      <OnClick>
        Baganator.CallbackRegistry:TriggerEvent("ShowCustomise")
      </OnClick>
    </Scripts>
  </Button>

  <Button name="BaganatorToggleBagSlotsButtonTemplate" virtual="true" inherits="BaganatorTooltipIconButtonTemplate">
    <KeyValues>
      <KeyValue key="tooltipHeader" value="BAGANATOR_L_BAG_SLOTS" type="global"/>
    </KeyValues>
    <Layers>
      <Layer level="ARTWORK">
        <Texture atlas="Banker">
          <Size x="17" y="17"/>
          <Anchors>
            <Anchor point="CENTER"/>
          </Anchors>
        </Texture>
      </Layer>
    </Layers>
  </Button>

  <Button name="BaganatorSortButtonTemplate" virtual="true" inherits="BaganatorTooltipIconButtonTemplate">
    <KeyValues>
      <KeyValue key="tooltipHeader" value="BAGANATOR_L_SORT" type="global"/>
    </KeyValues>
    <Scripts>
      <OnLoad>
        if Baganator.Constants.IsRetail then
          self.icon:SetSize(20, 20)
        end
        -- Disable sort button during combat as sorting is partially blocked by Blizzard
        self:RegisterEvent("PLAYER_REGEN_ENABLED")
        self:RegisterEvent("PLAYER_REGEN_DISABLED")
        self:SetEnabled(not InCombatLockdown())
      </OnLoad>
      <OnEvent>
        self:SetEnabled(event ~= "PLAYER_REGEN_DISABLED")
      </OnEvent>
    </Scripts>
    <Layers>
      <Layer level="ARTWORK">
        <Texture parentKey="icon" atlas="bags-button-autosort-up">
          <Size x="17" y="17"/>
          <Anchors>
            <Anchor point="CENTER"/>
          </Anchors>
        </Texture>
      </Layer>
    </Layers>
  </Button>

  <Button name="BaganatorTransferButtonTemplate" virtual="true" inherits="BaganatorTooltipIconButtonTemplate">
    <KeyValues>
      <KeyValue key="tooltipHeader" value="BAGANATOR_L_TRANSFER" type="global"/>
    </KeyValues>
    <Scripts>
      <OnLoad>
        -- Disable transfer button during combat as sorting is partially blocked by Blizzard
        self:RegisterEvent("PLAYER_REGEN_ENABLED")
        self:RegisterEvent("PLAYER_REGEN_DISABLED")
        self:SetEnabled(not InCombatLockdown())
      </OnLoad>
      <OnEvent>
        self:SetEnabled(event ~= "PLAYER_REGEN_DISABLED")
      </OnEvent>
    </Scripts>
    <Layers>
      <Layer level="ARTWORK">
        <Texture parentKey="icon" atlas="orderhalltalents-choice-arrow-large">
          <Size x="17" y="13"/>
          <Anchors>
            <Anchor point="CENTER"/>
          </Anchors>
        </Texture>
      </Layer>
    </Layers>
  </Button>

  <Button name="BaganatorToggleReagentsButtonTemplate" virtual="true" inherits="BaganatorTooltipIconButtonTemplate">
    <KeyValues>
      <KeyValue key="tooltipHeader" value="BAGANATOR_L_REAGENTS" type="global"/>
    </KeyValues>
    <Layers>
      <Layer level="ARTWORK">
        <Texture parentKey="icon">
          <Size x="17" y="17"/>
          <Anchors>
            <Anchor point="CENTER"/>
          </Anchors>
        </Texture>
      </Layer>
    </Layers>
    <Scripts>
      <OnLoad>
        if Baganator.Constants.IsRetail then
          self.icon:SetAtlas("Professions_Tracking_Herb")
          self.tooltipHeader = BAGANATOR_L_REAGENTS
        elseif Baganator.Constants.IsClassic then
          self.icon:SetTexture("Interface\\AddOns\\Baganator\\Assets\\spell_nature_moonkey")
          self.tooltipHeader = BAGANATOR_L_KEYS
        end
      </OnLoad>
    </Scripts>
  </Button>

  <Button name="BaganatorAllCharactersButtonTemplate" inherits="BaganatorTooltipIconButtonTemplate" virtual="true">
    <KeyValues>
      <KeyValue key="tooltipHeader" value="BAGANATOR_L_ALL_CHARACTERS" type="global"/>
    </KeyValues>
    <Layers>
      <Layer level="ARTWORK">
        <Texture atlas="socialqueuing-icon-group">
          <Size x="17" y="17"/>
          <Anchors>
            <Anchor point="CENTER"/>
          </Anchors>
        </Texture>
      </Layer>
    </Layers>
    <Scripts>
      <OnClick>
        Baganator.CallbackRegistry:TriggerEvent("CharacterSelectToggle")
      </OnClick>
    </Scripts>
  </Button>

  <Button name="BaganatorBankButtonTemplate" inherits="BaganatorTooltipIconButtonTemplate" virtual="true">
    <KeyValues>
      <KeyValue key="tooltipHeader" value="BAGANATOR_L_BANK" type="global"/>
    </KeyValues>
    <Layers>
      <Layer level="ARTWORK">
        <Texture parentKey="icon" atlas="VignetteLoot">
          <Size x="17" y="17"/>
          <Anchors>
            <Anchor point="CENTER"/>
          </Anchors>
        </Texture>
      </Layer>
    </Layers>
    <Scripts>
      <OnLoad>
        if Baganator.Constants.IsClassic then
          self.icon:SetSize(22, 22)
        end
      </OnLoad>
    </Scripts>
  </Button>

  <Button name="BaganatorGuildBankButtonTemplate" inherits="BaganatorTooltipIconButtonTemplate" virtual="true">
    <KeyValues>
      <KeyValue key="tooltipHeader" value="BAGANATOR_L_GUILD_BANK" type="global"/>
    </KeyValues>
    <Layers>
      <Layer level="ARTWORK">
        <Texture atlas="communities-guildbanner-background">
          <Size x="12" y="12"/>
          <Anchors>
            <Anchor point="CENTER"/>
          </Anchors>
        </Texture>
        <Texture atlas="communities-guildbanner-border">
          <Size x="12" y="12"/>
          <Anchors>
            <Anchor point="CENTER"/>
          </Anchors>
        </Texture>
      </Layer>
    </Layers>
  </Button>

  <Button name="BaganatorMegaSearchButtonTemplate" inherits="BaganatorTooltipIconButtonTemplate" virtual="true" motionScriptsWhileDisabled="true">
    <KeyValues>
      <KeyValue key="tooltipHeader" value="BAGANATOR_L_SEARCH_EVERYWHERE" type="global"/>
      <KeyValue key="tooltipText" value="BAGANATOR_L_SEARCH_EVERYWHERE_TOOLTIP_TEXT_2" type="global"/>
    </KeyValues>
    <Layers>
      <Layer level="ARTWORK">
        <Texture atlas="worldquest-icon-dungeon">
          <Size x="17" y="17"/>
          <Anchors>
            <Anchor point="CENTER"/>
          </Anchors>
        </Texture>
      </Layer>
    </Layers>
  </Button>
</Ui>
